jp_consumer_theory/__init__.py
jp_consumer_theory/optimization.py
jp_consumer_theory/plotting.py
tests/__init__.py
tests/test_optimization.py
tests/test_plotting.py
JP_Consumer_Theory-0.1.dist-info/METADATA
JP_Consumer_Theory-0.1.dist-info/WHEEL
JP_Consumer_Theory-0.1.dist-info/top_level.txt
JP_Consumer_Theory-0.1.dist-info/RECORD
