Metadata-Version: 2.1
Name: JP-Consumer-Theory
Version: 0.1
Summary: A Python package for consumer theory optimization and plotting
Home-page: https://github.com/Japulgarin/JP_Consumer-Theory
Author: Jorge Andres Pulgarin Barbosa
Author-email: japulgarin@uninorte.edu.co
License: MIT
Requires-Dist: sympy
Requires-Dist: numpy
Requires-Dist: scipy
Requires-Dist: matplotlib
